LICENSE.txt
MANIFEST.in
README.rst
requirements.txt
setup.cfg
setup.py
versioneer.py
docs/source/api.rst
docs/source/changelog.rst
docs/source/index.rst
docs/source/install.rst
elements_custom_s3fs.egg-info/PKG-INFO
elements_custom_s3fs.egg-info/SOURCES.txt
elements_custom_s3fs.egg-info/dependency_links.txt
elements_custom_s3fs.egg-info/not-zip-safe
elements_custom_s3fs.egg-info/requires.txt
elements_custom_s3fs.egg-info/top_level.txt
s3fs/__init__.py
s3fs/_version.py
s3fs/core.py
s3fs/errors.py
s3fs/mapping.py
s3fs/utils.py
s3fs/tests/__init__.py
s3fs/tests/test_mapping.py
s3fs/tests/test_s3fs.py
s3fs/tests/test_utils.py