Metadata-Version: 2.1
Name: elements-custom-s3fs
Version: 2021.11.4
Summary: Convenient Filesystem interface over S3
Home-page: http://github.com/fsspec/s3fs/
Maintainer: Martin Durant
Maintainer-email: mdurant@continuum.io
License: BSD
Keywords: s3,boto
Classifier: Development Status :: 4 - Beta
Classifier: Intended Audience :: Developers
Classifier: License :: OSI Approved :: BSD License
Classifier: Operating System :: OS Independent
Classifier: Programming Language :: Python :: 3.6
Classifier: Programming Language :: Python :: 3.7
Classifier: Programming Language :: Python :: 3.8
Classifier: Programming Language :: Python :: 3.9
Requires-Python: >= 3.6
Provides-Extra: awscli
Provides-Extra: boto3
License-File: LICENSE.txt
